idrt/__init__.py
idrt/config.py
idrt/contrastive_metric.py
idrt/cosine_metric.py
idrt/data.py
idrt/embedding_logger.py
idrt/eval.py
idrt/match.py
idrt/metric.py
idrt/model.py
idrt/model_classifier.py
idrt/model_cli.py
idrt/prepare_data.py
idrt/report.py
idrt/report_classifier.py
idrt/train.py
idrt/train_classifier.py
idrt/train_classifier_yaml.py
idrt/train_yaml.py
idrt/utilities.py
idrt/algorithm/__init__.py
idrt/algorithm/database_adapter.py
idrt/algorithm/prepare_data.py
idrt/algorithm/run_search.py
idrt/algorithm/utils.py
idrt-0.5.3.dist-info/METADATA
idrt-0.5.3.dist-info/WHEEL
idrt-0.5.3.dist-info/licenses/LICENSE
idrt-0.5.3.dist-info/RECORD
