Metadata-Version: 2.1
Name: idrt
Version: 0.5.3
Summary: A library that uses deep-learning to match contacts based on text-fields such as name and email.
Project-URL: Homepage, https://github.com/Jason94/identity-resolution
Project-URL: Bug Tracker, https://github.com/Jason94/identity-resolution/issues
Author-email: Jason Walker <JasonW94@gmail.com>
License-File: LICENSE
Classifier: License :: OSI Approved :: MIT License
Classifier: Operating System :: OS Independent
Classifier: Programming Language :: Python :: 3
Requires-Python: >=3.10
Requires-Dist: lightning
Requires-Dist: lightning[extra]
Requires-Dist: matplotlib
Requires-Dist: scikit-learn
Requires-Dist: seaborn
Requires-Dist: tensorboard
Requires-Dist: torch
Requires-Dist: torchaudio
Requires-Dist: torchvision
Provides-Extra: algorithm
Requires-Dist: annoy; extra == 'algorithm'
Requires-Dist: petl; extra == 'algorithm'
Requires-Dist: pypika; extra == 'algorithm'
Provides-Extra: test
Requires-Dist: expects; extra == 'test'
Requires-Dist: mamba; extra == 'test'
